README.md
setup.py
hse_de_project/AdamsMethod.py
hse_de_project/AdamsMethodIII.py
hse_de_project/AdamsMethodIV.py
hse_de_project/AdamsPC.py
hse_de_project/DEMethod.py
hse_de_project/EulerMethod.py
hse_de_project/ImplicitRungeKuttaMethodII.py
hse_de_project/ImprovedEulerMethod.py
hse_de_project/RungeKuttaMethodIV.py
hse_de_project/TaylorMethod.py
hse_de_project/__init__.py
hse_de_project/methods.py
hse_de_project.egg-info/PKG-INFO
hse_de_project.egg-info/SOURCES.txt
hse_de_project.egg-info/dependency_links.txt
hse_de_project.egg-info/top_level.txt