Metadata-Version: 1.0
Name: hse-de-project
Version: 0.0.13
Summary: HSE AMI Differential Equations Project
Home-page: https://github.com/kekekekule/Differential-equations-project
Author: Artem Streltsov
Author-email: adstreltsov@edu.hse.ru
License: MIT
Keywords: differential,equations,study
Platform: UNKNOWN
